MANIFEST.in
README.rst
setup.py
zeus
zeus_lab804.egg-info/PKG-INFO
zeus_lab804.egg-info/SOURCES.txt
zeus_lab804.egg-info/dependency_links.txt
zeus_lab804.egg-info/not-zip-safe
zeus_lab804.egg-info/requires.txt
zeus_lab804.egg-info/top_level.txt
zeusproject/__init__.py
zeusproject/commands.py
zeusproject/_module/__init__.py
zeusproject/_module/controllers.py
zeusproject/_module/forms.py
zeusproject/_module/models.py
zeusproject/_template/create.jinja
zeusproject/_template/edit.jinja
zeusproject/_template/get.jinja
zeusproject/_template/list.jinja
zeusproject/templates/.gitignore
zeusproject/templates/LICENSE
zeusproject/templates/README.rst
zeusproject/templates/fabfile.py
zeusproject/templates/manage.py
zeusproject/templates/requirements-dev.txt
zeusproject/templates/requirements.txt
zeusproject/templates/uwsgi.ini
zeusproject/templates/app/__init__.py
zeusproject/templates/app/config.py
zeusproject/templates/app/extensions.py
zeusproject/templates/app/admin/__init__.py
zeusproject/templates/app/admin/controllers.py
zeusproject/templates/app/admin/forms.py
zeusproject/templates/app/admin/models.py
zeusproject/templates/app/public/__init__.py
zeusproject/templates/app/public/controllers.py
zeusproject/templates/app/public/forms.py
zeusproject/templates/app/public/models.py
zeusproject/templates/app/users/__init__.py
zeusproject/templates/app/users/controllers.py
zeusproject/templates/app/users/forms.py
zeusproject/templates/app/users/models.py
zeusproject/templates/config/mongodb.service
zeusproject/templates/config/project_nginx.conf
zeusproject/templates/config/project_supervisor.conf
zeusproject/templates/static/css/bootstrap.css
zeusproject/templates/static/css/bootstrap.css.map
zeusproject/templates/static/css/site.css
zeusproject/templates/static/img/logo_zeus.svg
zeusproject/templates/static/js/app.js
zeusproject/templates/static/js/bootstrap.js
zeusproject/templates/templates/401.jinja
zeusproject/templates/templates/404.jinja
zeusproject/templates/templates/500.jinja
zeusproject/templates/templates/base.jinja
zeusproject/templates/templates/admin/index.html
zeusproject/templates/templates/admin/users/list.html
zeusproject/templates/templates/public/index.html
