Metadata-Version: 1.1
Name: zeus-lab804
Version: 0.1.2
Summary: Fast create scaffold of flask.
Home-page: https://github.com/murilobsd/zeus
Author: Lab804
Author-email: contato@lab804.com.br
License: BSD
Platform: any
Classifier: Environment :: Console
Classifier: Intended Audience :: Developers
Classifier: License :: OSI Approved :: BSD License
Classifier: Natural Language :: English
Classifier: Operating System :: OS Independent
Classifier: Natural Language :: English
Classifier: Operating System :: OS Independent
Classifier: Programming Language :: Python :: 3
Classifier: Programming Language :: Python :: 3.3
Classifier: Programming Language :: Python :: 3.4
Classifier: Programming Language :: Python :: 3.5
Classifier: Topic :: Internet :: WWW/HTTP :: Dynamic Content
